onlyoffice/OnlyOffice.py
onlyoffice/__init__.py
onlyoffice-0.1.0.dist-info/LICENSE
onlyoffice-0.1.0.dist-info/METADATA
onlyoffice-0.1.0.dist-info/WHEEL
onlyoffice-0.1.0.dist-info/top_level.txt
onlyoffice-0.1.0.dist-info/RECORD
