Metadata-Version: 2.1
Name: onlyoffice
Version: 0.1.0
Summary: Python API for OnlyOffice.
Home-page: https://github.com/casiez/onlyoffice
Author: Géry Casiez
Author-email: gery.casiez@gmail.com
Classifier: Programming Language :: Python :: 3
Classifier: License :: OSI Approved :: MIT License
License-File: LICENSE
Requires-Dist: requests
